MANIFEST.in
README.rst
setup.py
docs/HISTORY.rst
docs/INSTALL.txt
docs/LICENSE.GPL
docs/LICENSE.txt
redturtle/__init__.py
redturtle.subsites.egg-info/PKG-INFO
redturtle.subsites.egg-info/SOURCES.txt
redturtle.subsites.egg-info/dependency_links.txt
redturtle.subsites.egg-info/entry_points.txt
redturtle.subsites.egg-info/namespace_packages.txt
redturtle.subsites.egg-info/not-zip-safe
redturtle.subsites.egg-info/requires.txt
redturtle.subsites.egg-info/top_level.txt
redturtle/subsites/__init__.py
redturtle/subsites/configure.zcml
redturtle/subsites/skinswitcher.py
redturtle/subsites/skinswitcher.zcml
redturtle/subsites/tests.py
redturtle/subsites/adapter/__init__.py
redturtle/subsites/adapter/configure.zcml
redturtle/subsites/adapter/traverser.py
redturtle/subsites/backend/__init__.py
redturtle/subsites/backend/configure.zcml
redturtle/subsites/backend/interfaces.py
redturtle/subsites/frontend/__init__.py
redturtle/subsites/frontend/configure.zcml
redturtle/subsites/frontend/browser/__init__.py
redturtle/subsites/frontend/browser/configure.zcml
redturtle/subsites/frontend/browser/interfaces.py
redturtle/subsites/frontend/browser/scripts.py
redturtle/subsites/frontend/browser/styles.py
redturtle/subsites/frontend/viewlets/__init__.py
redturtle/subsites/frontend/viewlets/configure.zcml
redturtle/subsites/frontend/viewlets/logo.py
redturtle/subsites/locales/it/LC_MESSAGES/redturtle.subsites.mo
redturtle/subsites/locales/it/LC_MESSAGES/redturtle.subsites.po